movieclipper/__init__.py
movieclipper-0.0.0.dist-info/METADATA
movieclipper-0.0.0.dist-info/WHEEL
movieclipper-0.0.0.dist-info/RECORD
