Metadata-Version: 2.4
Name: movieclipper
Version: 0.0.0
Summary: CLI to cut video clips with ffmpeg, fuzzy title matching, and audio stream selection.
Author: Sebastien De Reviere
Classifier: Development Status :: 1 - Planning
Requires-Python: >=3.10
